fireferret/__init__.py
fireferret/clustering/kmeans.py
fireferret/utils/logger.py
fireferret-0.1.0.dist-info/LICENSE
fireferret-0.1.0.dist-info/METADATA
fireferret-0.1.0.dist-info/WHEEL
fireferret-0.1.0.dist-info/top_level.txt
fireferret-0.1.0.dist-info/RECORD
