Metadata-Version: 2.1
Name: fireferret
Version: 0.1.0
Summary: Repository containing different ML algorithms
Author: Dinno Koluh
Requires-Python: >=3.12
License-File: LICENSE
